dunderlab/docs/__init__.py
dunderlab/docs/scripts/__init__.py
dunderlab/docs/scripts/dunderlab_docs.py
dunderlab/docs/static/dunderlab_custom.css
dunderlab/docs/static/roboto_font.css
dunderlab/docs/templates/module.rst_t
dunderlab/docs/templates/package.rst_t
dunderlab/docs/templates/toc.rst_t
dunderlab_docs-1.20.dist-info/licenses/LICENSE
dunderlab_docs-1.20.dist-info/METADATA
dunderlab_docs-1.20.dist-info/WHEEL
dunderlab_docs-1.20.dist-info/entry_points.txt
dunderlab_docs-1.20.dist-info/top_level.txt
dunderlab_docs-1.20.dist-info/RECORD
