Metadata-Version: 2.4
Name: dunderlab-docs
Version: 1.20
Author-email: Yeison Cardona <yencardonaal@unal.edu.co>
Maintainer-email: Yeison Cardona <yencardonaal@unal.edu.co>
License: Simplified BSD License
Classifier: Development Status :: 4 - Beta
Classifier: Intended Audience :: Developers
Classifier: Programming Language :: Python :: 3.7
Classifier: Programming Language :: Python :: 3.8
Classifier: Topic :: Scientific/Engineering
Classifier: Topic :: Software Development :: Libraries
Classifier: Topic :: Software Development :: Libraries :: Application Frameworks
Classifier: Topic :: Software Development :: Libraries :: Python Modules
Classifier: Topic :: System :: Hardware :: Hardware Drivers
Requires-Python: >=3.8
License-File: LICENSE
Requires-Dist: nbsphinx
Requires-Dist: jupytext
Requires-Dist: sphinx
Requires-Dist: urllib3
Requires-Dist: ipython
Requires-Dist: ipykernel
Requires-Dist: sphinxcontrib-bibtex
Requires-Dist: pygments
Dynamic: license-file
